keycloaknanny.py
keycloaknanny-23.0.0.dist-info/METADATA
keycloaknanny-23.0.0.dist-info/WHEEL
keycloaknanny-23.0.0.dist-info/licenses/LICENSE.txt
keycloaknanny-23.0.0.dist-info/RECORD
