Metadata-Version: 2.1
Name: keycloaknanny
Version: 23.0.0
Summary: Simple Python library for managing a toy Keycloak instance.
Project-URL: Documentation, https://github.com/soxofaan/keycloak-nanny#readme
Project-URL: Issues, https://github.com/soxofaan/keycloak-nanny/issues
Project-URL: Source, https://github.com/soxofaan/keycloak-nanny
Author-email: Stefaan Lippens <soxofaan@gmail.com>
License-Expression: MIT
License-File: LICENSE.txt
Keywords: keycloak
Classifier: Development Status :: 4 - Beta
Classifier: License :: OSI Approved :: MIT License
Classifier: Operating System :: OS Independent
Classifier: Programming Language :: Python
Classifier: Programming Language :: Python :: 3.7
Classifier: Programming Language :: Python :: 3.8
Classifier: Programming Language :: Python :: 3.9
Classifier: Programming Language :: Python :: 3.10
Classifier: Programming Language :: Python :: 3.11
Classifier: Programming Language :: Python :: Implementation :: CPython
Classifier: Programming Language :: Python :: Implementation :: PyPy
Requires-Python: >=3.7
Requires-Dist: requests>2.28.0
